test/__init__.py
test/mock_framework.py
test/test_cashflow.py
test/test_historicaldata.py
test/resources/__init__.py
yahoofinance/__init__.py
yahoofinance/assetprofile.py
yahoofinance/balancesheet.py
yahoofinance/cashflow.py
yahoofinance/dataconfigs.py
yahoofinance/historicaldata.py
yahoofinance/incomestatement.py
yahoofinance/interfaces.py
yahoofinance-0.0.2.dist-info/LICENSE
yahoofinance-0.0.2.dist-info/METADATA
yahoofinance-0.0.2.dist-info/WHEEL
yahoofinance-0.0.2.dist-info/top_level.txt
yahoofinance-0.0.2.dist-info/RECORD
