Metadata-Version: 2.1
Name: yahoofinance
Version: 0.0.2
Summary: A library to retrieve data from Yahoo Finance
Home-page: https://github.com/mqtran01/python-yahoo-finance
Author: Michael Tran
Author-email: example@example.com
License: UNKNOWN
Platform: UNKNOWN
Classifier: Programming Language :: Python :: 3
Classifier: License :: OSI Approved :: MIT License
Classifier: Operating System :: OS Independent
Classifier: Development Status :: 2 - Pre-Alpha
Classifier: Topic :: Office/Business :: Financial
Classifier: Topic :: Office/Business :: Financial :: Investment
Classifier: Topic :: Software Development :: Libraries :: Python Modules
Classifier: Programming Language :: Python :: 3.6
Classifier: Programming Language :: Python :: 3.7
